[
  {
    "title": "Străzi Reper",
    "amount": 3,
    "description": "Activează clădiri aflate pe strada Anastasie Simu pentru a finaliza aventura!",
    "xp": 30
  },
   {
    "title": "Arhitecți Celebri",
    "amount": 3,
    "description": "Activează clădiri proiectate de arhitectul Marcel Maller pentru a finaliza aventura!",
    "xp": 30
  },
   {
    "title": "Clădiri Monument (B)",
    "amount": 12,
    "description": "Activează clădiri clasate drept monumente istorice de interes local pentru a finaliza aventura!",
    "xp": 120
  }

]









