[
  {
    "title": "Arhitecți Celebri",
    "amount": 8,
    "description": "Activează clădiri proiectate de arhitectul Ion D. Berindey pentru a finaliza aventura!",
    "xp": 80
  },
  {
    "title": "Perioade Istorice",
    "amount": 8,
    "description": "Activează clădiri construite în perioada socialistă (1965-1989) pentru a finaliza aventura!",
    "xp": 80
  },
  {
    "title": "Clădiri Monument (B)",
    "amount": 16,
    "description": "Activează clădiri clasate drept monumente istorice de interes local pentru a finaliza aventura!",
    "xp": 160
  }
]
