[
  {
    "title": "Arhitecți Celebri",
    "amount": 9,
    "description": "Activează clădiri proiectate de arhitectul Paul Gottereau pentru a finaliza aventura!",
    "xp": 90
  },
  {
    "title": "Perioade Istorice",
    "amount": 18,
    "description": "Activează clădiri construite în perioada socialistă (1965-1989) pentru a finaliza aventura!",
    "xp": 180
  },
  {
    "title": "Clădiri Monument (B)",
    "amount": 12,
    "description": "Activează clădiri clasate drept monumente istorice de interes local pentru a finaliza aventura!",
    "xp": 120
  }
]
