[
  {
    "title": "Perioade Istorice",
    "amount": 15,
    "description": "Activează clădiri construite în perioada interbelică (1918-1939) pentru a finaliza aventura!",
    "xp": 150
  },
  {
    "title": "Clădiri Monument (A)",
    "amount": 21,
    "description": "Activează clădiri clasate drept monumente istorice de interes național pentru a finaliza aventura!",
    "xp": 210
  },
  {
    "title": "Stiluri Arhitecturale",
    "amount": 23,
    "description": "Activează clădiri realizate în stil Art Deco pentru a finaliza aventura!",
    "xp": 230
  }
]
